README.rst
setup.py
selenate/__init__.py
selenate/elements.py
selenate/exceptions.py
selenate/selenate.py
selenate/tests.py
selenate/urls.py
selenate.egg-info/PKG-INFO
selenate.egg-info/SOURCES.txt
selenate.egg-info/dependency_links.txt
selenate.egg-info/requires.txt
selenate.egg-info/top_level.txt