Metadata-Version: 1.0
Name: selenate
Version: 0.4.0
Summary: Web Automation made easy
Home-page: https://github.com/wmak/selenate
Author: William Mak
Author-email: WilliamSYMak@gmail.com
License: Apache 2.0
Platform: UNKNOWN
